calibrated_explanations/__init__.py
calibrated_explanations/plotting.py
calibrated_explanations/py.typed
calibrated_explanations/serialization.py
calibrated_explanations/api/__init__.py
calibrated_explanations/api/config.py
calibrated_explanations/api/params.py
calibrated_explanations/api/quick.py
calibrated_explanations/cache/__init__.py
calibrated_explanations/cache/cache.py
calibrated_explanations/cache/explanation_cache.py
calibrated_explanations/calibration/__init__.py
calibrated_explanations/calibration/interval_learner.py
calibrated_explanations/calibration/interval_regressor.py
calibrated_explanations/calibration/state.py
calibrated_explanations/calibration/summaries.py
calibrated_explanations/calibration/venn_abers.py
calibrated_explanations/core/__init__.py
calibrated_explanations/core/calibrated_explainer.py
calibrated_explanations/core/calibration_helpers.py
calibrated_explanations/core/calibration_metrics.py
calibrated_explanations/core/config_helpers.py
calibrated_explanations/core/difficulty_estimator_helpers.py
calibrated_explanations/core/discretizer_config.py
calibrated_explanations/core/exceptions.py
calibrated_explanations/core/narrative_generator.py
calibrated_explanations/core/prediction_helpers.py
calibrated_explanations/core/quick.py
calibrated_explanations/core/test.py
calibrated_explanations/core/validation.py
calibrated_explanations/core/wrap_explainer.py
calibrated_explanations/core/calibration/__init__.py
calibrated_explanations/core/calibration/interval_learner.py
calibrated_explanations/core/calibration/interval_regressor.py
calibrated_explanations/core/calibration/state.py
calibrated_explanations/core/calibration/summaries.py
calibrated_explanations/core/calibration/venn_abers.py
calibrated_explanations/core/explain/__init__.py
calibrated_explanations/core/explain/_base.py
calibrated_explanations/core/explain/_computation.py
calibrated_explanations/core/explain/_feature_filter.py
calibrated_explanations/core/explain/_helpers.py
calibrated_explanations-0.10.0.dist-info/licenses/LICENSE
calibrated_explanations-0.10.0.dist-info/METADATA
calibrated_explanations-0.10.0.dist-info/WHEEL
calibrated_explanations-0.10.0.dist-info/entry_points.txt
calibrated_explanations-0.10.0.dist-info/top_level.txt
calibrated_explanations-0.10.0.dist-info/RECORD
