Metadata-Version: 2.4
Name: calibrated_explanations
Version: 0.10.0
Summary: Extract calibrated explanations from machine learning models.
Author-email: Helena Löfström <helena.lofstrom@ju.se>, Tuwe Löfström <tuwe.lofstrom@ju.se>
License: BSD-3-Clause
Project-URL: Documentation, https://calibrated-explanations.readthedocs.io/en/latest/?badge=latest
Project-URL: Changelog, https://github.com/Moffran/calibrated_explanations/blob/main/CHANGELOG.md
Project-URL: Bug Tracker, https://github.com/Moffran/calibrated_explanations/issues
Project-URL: Repository, https://github.com/Moffran/calibrated_explanations
Classifier: Development Status :: 3 - Alpha
Classifier: Programming Language :: Python :: 3
Classifier: License :: OSI Approved :: BSD License
Classifier: Operating System :: OS Independent
Requires-Python: >=3.8
License-File: LICENSE
Requires-Dist: cachetools
Requires-Dist: pympler
Requires-Dist: crepes
Requires-Dist: venn-abers
Requires-Dist: ipython
Requires-Dist: lime
Requires-Dist: matplotlib
Requires-Dist: numpy
Requires-Dist: pandas
Requires-Dist: scikit-learn
Requires-Dist: pyyaml
Provides-Extra: viz
Requires-Dist: matplotlib; extra == "viz"
Provides-Extra: lime
Requires-Dist: lime; extra == "lime"
Provides-Extra: notebooks
Requires-Dist: ipython; extra == "notebooks"
Requires-Dist: jupyter; extra == "notebooks"
Requires-Dist: nbconvert; extra == "notebooks"
Requires-Dist: matplotlib; extra == "notebooks"
Provides-Extra: dev
Requires-Dist: pytest; extra == "dev"
Requires-Dist: pytest-cov; extra == "dev"
Requires-Dist: ruff; extra == "dev"
Requires-Dist: mypy; extra == "dev"
Requires-Dist: jsonschema; extra == "dev"
Requires-Dist: pydocstyle; extra == "dev"
Requires-Dist: nbqa; extra == "dev"
Provides-Extra: eval
Requires-Dist: shap; extra == "eval"
Requires-Dist: seaborn; extra == "eval"
Provides-Extra: external-plugins
Requires-Dist: numpy>=1.24; extra == "external-plugins"
Requires-Dist: pandas>=2.0; extra == "external-plugins"
Requires-Dist: scikit-learn>=1.3; extra == "external-plugins"
Dynamic: license-file
